rq_result/__init__.py
rq_result/admin.py
rq_result/apps.py
rq_result/backends.py
rq_result/migrations/0001_initial.py
rq_result/migrations/__init__.py
rq_result/models.py
rq_result/tests.py
rq_result/views.py
rq_result-0.1.1.dist-info/WHEEL
rq_result-0.1.1.dist-info/METADATA
rq_result-0.1.1.dist-info/RECORD
