Metadata-Version: 2.3
Name: rq-result
Version: 0.1.1
Summary: RQ result backend for django.
Author: pyqf
Requires-Dist: django>=4.1.13
Requires-Python: >=3.11
